CONTRIBUTORS.txt
LICENSE.txt
MANIFEST.in
README.rst
requirements.txt
setup.cfg
setup.py
test/test_vbbvg.py
vbbvg/__init__.py
vbbvg/__main__.py
vbbvg/vbbvg.py
vbbvg/vbbvg_Levenshtein.py
vbbvg/vbbvg_stops.csv
vbbvg.egg-info/PKG-INFO
vbbvg.egg-info/SOURCES.txt
vbbvg.egg-info/dependency_links.txt
vbbvg.egg-info/entry_points.txt
vbbvg.egg-info/pbr.json
vbbvg.egg-info/requires.txt
vbbvg.egg-info/top_level.txt