Metadata-Version: 1.1
Name: vbbvg
Version: 0.0.1
Summary: Fetch and display real-time departure times for VBB/BVG public transport
Home-page: https://github.com/deeplook/vbbvg
Author: Dinu Gherman
Author-email: gherman@darwin.in-berlin.de
License: GPL
Keywords: real-time,transport-data
Platform: UNKNOWN
Classifier: Environment :: Console
Classifier: Intended Audience :: Developers
Classifier: Programming Language :: Python :: 2.7
Classifier: License :: OSI Approved :: GNU General Public License (GPL)
